envidat_converter-0.2.2.dist-info/licenses/LICENSE
envidat_converters/__init__.py
envidat_converters/envidat_converter_cli.py
envidat_converters/api/__init__.py
envidat_converters/api/envidat_converter_api.py
envidat_converters/api/envidat_internal_dataset_api.py
envidat_converters/api/main.py
envidat_converters/api/router.py
envidat_converters/logic/__init__.py
envidat_converters/logic/constants.py
envidat_converters/logic/converter_service.py
envidat_converters/logic/exceptions.py
envidat_converters/logic/general_helpers.py
envidat_converters/logic/read_config.py
envidat_converters/logic/ckan_helper/__init__.py
envidat_converters/logic/ckan_helper/ckan_helper.py
envidat_converters/logic/converter_logic/__init__.py
envidat_converters/logic/converter_logic/encoding_helper.py
envidat_converters/logic/converter_logic/envidat_to_datacite.py
envidat_converters/logic/converter_logic/envidat_to_jsonld.py
envidat_converters/logic/converter_logic/envidat_to_signposting.py
envidat_converters/logic/converter_logic/signposting.py
envidat_converters/logic/converter_logic/datacite_helpers/__init__.py
envidat_converters/logic/converter_logic/datacite_helpers/affilation_helper.py
envidat_converters/logic/converter_logic/datacite_helpers/contributor_helper.py
envidat_converters/logic/converter_logic/datacite_helpers/creators_helper.py
envidat_converters/logic/converter_logic/datacite_helpers/description_helper.py
envidat_converters/logic/converter_logic/datacite_helpers/format_helper.py
envidat_converters/logic/converter_logic/datacite_helpers/geolocation_helper.py
envidat_converters/logic/converter_logic/datacite_helpers/related_items_and_identifiers_helper.py
envidat_converters/logic/converter_logic/datacite_helpers/sizes_helper.py
envidat_converters/logic/converter_logic/datacite_helpers/tags.py
envidat_converters/logic/converter_logic/datacite_helpers/various_helper.py
envidat_converters/logic/converter_logic/old_converters/bibtex_converter.py
envidat_converters/logic/converter_logic/old_converters/dcat_ap_converter.py
envidat_converter-0.2.2.dist-info/METADATA
envidat_converter-0.2.2.dist-info/WHEEL
envidat_converter-0.2.2.dist-info/entry_points.txt
envidat_converter-0.2.2.dist-info/top_level.txt
envidat_converter-0.2.2.dist-info/RECORD
