Metadata-Version: 2.4
Name: envidat-converter
Version: 0.2.2
Summary: Converters for EnviDat metadata
Author-email: Yasmin Waldeck <yasmin.waldeck@wsl.ch>
License-Expression: MIT
Project-URL: Repository, https://gitlabext.wsl.ch/EnviDat/envidat-converter/
Project-URL: Changelog, https://gitlabext.wsl.ch/EnviDat/envidat-converter/-/blob/main/CHANGELOG.md
Keywords: envidat
Requires-Python: >=3.10
License-File: LICENSE
Requires-Dist: requests~=2.32.4
Requires-Dist: parameterized~=0.9.0
Requires-Dist: ckanapi~=4.8
Requires-Dist: validators~=0.35.0
Requires-Dist: xmltodict~=0.14.2
Requires-Dist: click~=8.2.1
Requires-Dist: uvicorn~=0.38.0
Requires-Dist: fastapi~=0.120.1
Requires-Dist: python-dateutil~=2.9.0.post0
Requires-Dist: httpx~=0.28.1
Requires-Dist: pytest~=8.4.1
Requires-Dist: shapely>=2.1.2
Dynamic: license-file
